LICENSE.txt
investify/__init__.py
investify/investify.py
investify/investing.py
investify/sendtext.py
investify-0.0.4.dist-info/entry_points.txt
investify-0.0.4.dist-info/LICENSE.txt
investify-0.0.4.dist-info/WHEEL
investify-0.0.4.dist-info/METADATA
investify-0.0.4.dist-info/RECORD
