Metadata-Version: 2.1
Name: investify
Version: 0.0.4
Summary: Get automated price alert based on investing.com prices
Home-page: https://github.com/abhi-g80/investify
License: MIT
Keywords: investing,whatsapp,finance,python,automation
Author: Abhishek Guha
Author-email: abhi.workspace@gmail.com
Requires-Python: >=3.6,<4.0
Classifier: Environment :: Console
Classifier: License :: OSI Approved :: MIT License
Classifier: Operating System :: OS Independent
Classifier: Programming Language :: Python :: 3
Classifier: Programming Language :: Python :: 3.6
Classifier: Programming Language :: Python :: 3.7
Classifier: Programming Language :: Python :: 3.8
Classifier: Topic :: Software Development :: Libraries :: Python Modules
Classifier: Topic :: Utilities
Requires-Dist: click (>=7.1.1,<8.0.0)
Requires-Dist: lxml (>=4.5.0,<5.0.0)
Requires-Dist: requests (>=2.23.0,<3.0.0)
Requires-Dist: twilio (>=6.38.0,<7.0.0)
Project-URL: Repository, https://github.com/abhi-g80/investify
